bob/__init__.py
bob/admin.py
bob/auth.py
bob/books.py
bob/data_store.py
bob/main.py
bob/menu.py
bob/validators.py
bob_lms-0.1.8.dist-info/licenses/LICENSE
bob_lms-0.1.8.dist-info/METADATA
bob_lms-0.1.8.dist-info/WHEEL
bob_lms-0.1.8.dist-info/entry_points.txt
bob_lms-0.1.8.dist-info/top_level.txt
bob_lms-0.1.8.dist-info/RECORD
