Metadata-Version: 2.4
Name: bob-lms
Version: 0.1.8
Summary: B.O.B — A Python-based CLI Library Management System
Author: Anirudh S, Arnav Prakash, Arvind Bhaskar
License: MIT License
Requires-Python: >=3.8
License-File: LICENSE
Dynamic: license-file
